dlo/__init__.py
dlo/main.py
dlo/utils.py
dlo-0.2.1.dist-info/LICENSE.md
dlo-0.2.1.dist-info/METADATA
dlo-0.2.1.dist-info/WHEEL
dlo-0.2.1.dist-info/top_level.txt
dlo-0.2.1.dist-info/RECORD
