Metadata-Version: 2.1
Name: dlo
Version: 0.2.1
Summary: A lightweight, dynamic Python client to pull NBA data from stats.nba.com.
Home-page: https://github.com/avkondepudi/dlo
Author: Akhil Kondepudi
Author-email: akhil.compsci79@gmail.com
License: UNKNOWN
Keywords: statistics data nba
Platform: UNKNOWN
Classifier: Development Status :: 5 - Production/Stable
Classifier: Intended Audience :: Developers
Classifier: Topic :: Software Development :: Build Tools
Classifier: License :: OSI Approved :: GNU General Public License v3 (GPLv3)
Classifier: Programming Language :: Python
Requires-Python: >=2.6
Requires-Dist: requests
